GeologicalToolbox/AbstractLog.py
GeologicalToolbox/Constants.py
GeologicalToolbox/DBHandler.py
GeologicalToolbox/Exceptions.py
GeologicalToolbox/GeoObject.py
GeologicalToolbox/Geometries.py
GeologicalToolbox/Properties.py
GeologicalToolbox/Requests.py
GeologicalToolbox/Stratigraphy.py
GeologicalToolbox/WellLogs.py
GeologicalToolbox/Wells.py
GeologicalToolbox/__init__.py
GeologicalToolbox/tests/__init__.py
GeologicalToolbox/tests/test_GeoPoint.py
GeologicalToolbox/tests/test_Line.py
GeologicalToolbox/tests/test_PropLogs.py
GeologicalToolbox/tests/test_Requests.py
GeologicalToolbox/tests/test_Stratigraphy.py
GeologicalToolbox/tests/test_Well.py
GeologicalToolbox-0.1.2b1.dist-info/DESCRIPTION.rst
GeologicalToolbox-0.1.2b1.dist-info/METADATA
GeologicalToolbox-0.1.2b1.dist-info/RECORD
GeologicalToolbox-0.1.2b1.dist-info/WHEEL
GeologicalToolbox-0.1.2b1.dist-info/metadata.json
GeologicalToolbox-0.1.2b1.dist-info/top_level.txt
