Metadata-Version: 2.0
Name: GeologicalToolbox
Version: 0.1.2b1
Summary: A python module for processing and storing geological data.
Home-page: https://github.com/stdonn/GeologicalToolbox
Author: Stephan Donndorf
Author-email: stephan@donndorf.info
License: MIT
Keywords: Geology Modelling SQLAlchemy
Platform: UNKNOWN
Classifier: Development Status :: 4 - Beta
Classifier: Intended Audience :: Developers
Classifier: Intended Audience :: Other Audience
Classifier: Intended Audience :: Science/Research
Classifier: License :: OSI Approved :: MIT License
Classifier: Programming Language :: Python :: 2
Classifier: Programming Language :: Python :: 2.7
Classifier: Programming Language :: Python :: 3
Classifier: Programming Language :: Python :: 3.4
Classifier: Programming Language :: Python :: 3.5
Classifier: Programming Language :: Python :: 3.6
Classifier: Natural Language :: English
Classifier: Topic :: Database :: Front-Ends
Classifier: Topic :: Documentation :: Sphinx
Classifier: Topic :: Scientific/Engineering :: GIS
Classifier: Topic :: Software Development :: Libraries
Classifier: Topic :: Software Development :: Libraries :: Python Modules
Requires-Python: >=2.6, !=3.0.*, !=3.1.*, !=3.2.*
Requires-Dist: SQLAlchemy (>=1.2)
Requires-Dist: typing
Provides-Extra: dev
Requires-Dist: Sphinx; extra == 'dev'
Requires-Dist: sphinxjp.themes.basicstrap; extra == 'dev'
